mlservicewrapper/config/__init__.py
mlservicewrapper/config/configuration.py
mlservicewrapper_config-0.3.dist-info/LICENSE
mlservicewrapper_config-0.3.dist-info/METADATA
mlservicewrapper_config-0.3.dist-info/WHEEL
mlservicewrapper_config-0.3.dist-info/top_level.txt
mlservicewrapper_config-0.3.dist-info/RECORD
