Metadata-Version: 2.1
Name: mlservicewrapper-config
Version: 0.3
Summary: Configuration helpers for ml services
Home-page: https://github.com/ml-service-wrapper/ml-service-wrapper-config
Author: Matthew Haugen
License: UNKNOWN
Platform: UNKNOWN
Requires-Python: >=3.6
